schemachange/__init__.py
schemachange/cli.py
schemachange_wo_pandas-3.6.1.dist-info/LICENSE
schemachange_wo_pandas-3.6.1.dist-info/METADATA
schemachange_wo_pandas-3.6.1.dist-info/WHEEL
schemachange_wo_pandas-3.6.1.dist-info/entry_points.txt
schemachange_wo_pandas-3.6.1.dist-info/top_level.txt
schemachange_wo_pandas-3.6.1.dist-info/RECORD
