Metadata-Version: 2.1
Name: schemachange-wo-pandas
Version: 3.6.1
Summary: A Database Change Management tool for Snowflake
Home-page: https://github.com/Snowflake-Labs/schemachange
Author: jamesweakley/jeremiahhansen
License: Apache-2.0
Classifier: License :: OSI Approved :: Apache Software License
Classifier: Operating System :: OS Independent
Classifier: Programming Language :: Python :: 3
Classifier: Programming Language :: Python :: 3 :: Only
Requires-Python: >=3.8
License-File: LICENSE
Requires-Dist: jinja2 ~=3.0
Requires-Dist: pyyaml ~=6.0
Requires-Dist: snowflake-connector-python <4.0,>=2.8
Provides-Extra: dev
Requires-Dist: pytest ; extra == 'dev'
